{
  "config": {
    "device": "mps",
    "model_name": "yolov8n.pt",
    "batch_size": 4,
    "num_cameras": 4,
    "use_fp16": false,
    "use_gpu_preprocess": false,
    "backend": "pytorch"
  },
  "pipeline": {
    "runtime_s": 60.18912196159363,
    "total_frames": 1692,
    "overall_fps": 28.11139197344757,
    "avg_latency_ms": 577.0309705542617,
    "per_camera": {
      "2": {
        "frames": 273,
        "fps": 4.535703314864768,
        "avg_latency": 0.5889270593831827,
        "detections": 147
      },
      "0": {
        "frames": 541,
        "fps": 8.988335140446297,
        "avg_latency": 0.6004847493057109,
        "detections": 2674
      },
      "3": {
        "frames": 616,
        "fps": 10.23440747969486,
        "avg_latency": 0.5969322350892153,
        "detections": 1776
      },
      "1": {
        "frames": 262,
        "fps": 4.352946038441645,
        "avg_latency": 0.46941530067502085,
        "detections": 208
      }
    }
  },
  "detector": {
    "total_detections": 4805,
    "inference_count": 1692,
    "avg_inference_time": 0.028657417770818615,
    "avg_fps": 34.894979303344066,
    "device": "mps",
    "model": "yolov8n.pt",
    "fp16": false,
    "gpu_preprocess": false
  },
  "profiler": {
    "duration": 58.45327877998352,
    "avg_cpu_percent": 12.436842105263159,
    "max_cpu_percent": 44.6,
    "avg_ram_gb": 9.558935065018503,
    "max_ram_gb": 10.00360107421875,
    "camera_2_avg_fps": 8.483507006842236,
    "camera_2_avg_latency": 0.27096655439426603,
    "camera_0_avg_fps": 16.649663006409476,
    "camera_0_avg_latency": 0.2924087529270497,
    "camera_3_avg_fps": 18.919718046696627,
    "camera_3_avg_latency": 0.29795524332914275,
    "camera_1_avg_fps": 8.140046808629709,
    "camera_1_avg_latency": 0.22668337769333777
  }
}